irrectum/__init__.py
irrectum/abc_metrics.py
irrectum-0.1.2.dist-info/METADATA
irrectum-0.1.2.dist-info/WHEEL
irrectum-0.1.2.dist-info/top_level.txt
irrectum-0.1.2.dist-info/RECORD
