Metadata-Version: 2.2
Name: irrectum
Version: 0.1.2
Summary: Metrics for Evaluating Model Quality
Author: Aksyanov Rustam
Author-email: akrustamru@gmail.com
Requires-Python: >=3.10
Requires-Dist: numpy>=1.26.0
Requires-Dist: setuptools>=69.1.0
Dynamic: author
Dynamic: author-email
Dynamic: requires-python
